["{\"id\": \"349d74c4-c5fa-4850-bd7c-1204bc805b5d\", \"nome\": \"Nicol\\u00f2\", \"cognome\": \"Sanse\", \"score\": 0, \"email\": \"aaaaa@gmail.com\", \"password\": \"pass\"}", "{\"id\": \"2f9bf075-e5df-43b1-8deb-6931a885d92f\", \"nome\": \"marco\", \"cognome\": \"fgoiiorwofj\", \"score\": 0, \"email\": \"b@gmail.com\", \"password\": \"pass\"}"],"{\"id\": \"8df934ab-dc87-4580-a50f-66d9d4bd538b\", \"nome\": \"fra\", \"cognome\": \"ijfwo\", \"score\": 0, \"email\": \"k@gmail.com\", \"password\": \"pass\"}"